odoo/addons/website_snippet_timeline/README.rst
odoo/addons/website_snippet_timeline/__init__.py
odoo/addons/website_snippet_timeline/__manifest__.py
odoo/addons/website_snippet_timeline/i18n/website_snippet_timeline.pot
odoo/addons/website_snippet_timeline/readme/CONTRIBUTORS.rst
odoo/addons/website_snippet_timeline/readme/DESCRIPTION.rst
odoo/addons/website_snippet_timeline/readme/USAGE.rst
odoo/addons/website_snippet_timeline/static/description/icon.png
odoo/addons/website_snippet_timeline/static/description/index.html
odoo/addons/website_snippet_timeline/static/description/screenshot-medium.png
odoo/addons/website_snippet_timeline/static/description/screenshot-small.png
odoo/addons/website_snippet_timeline/static/description/screenshot.png
odoo/addons/website_snippet_timeline/static/src/img/snippet-item.png
odoo/addons/website_snippet_timeline/static/src/img/snippet.png
odoo/addons/website_snippet_timeline/static/src/js/editor.js
odoo/addons/website_snippet_timeline/static/src/less/frontend.less
odoo/addons/website_snippet_timeline/templates/assets.xml
odoo/addons/website_snippet_timeline/templates/snippets.xml
odoo11_addon_website_snippet_timeline-11.0.1.0.0.99.dev7.dist-info/METADATA
odoo11_addon_website_snippet_timeline-11.0.1.0.0.99.dev7.dist-info/WHEEL
odoo11_addon_website_snippet_timeline-11.0.1.0.0.99.dev7.dist-info/top_level.txt
odoo11_addon_website_snippet_timeline-11.0.1.0.0.99.dev7.dist-info/RECORD
